ovmsclient/__init__.py
ovmsclient/custom/__init__.py
ovmsclient/custom/management_client.py
ovmsclient/tfs_compat/__init__.py
ovmsclient/tfs_compat/base/__init__.py
ovmsclient/tfs_compat/base/errors.py
ovmsclient/tfs_compat/base/requests.py
ovmsclient/tfs_compat/base/responses.py
ovmsclient/tfs_compat/base/serving_client.py
ovmsclient/tfs_compat/grpc/__init__.py
ovmsclient/tfs_compat/grpc/requests.py
ovmsclient/tfs_compat/grpc/responses.py
ovmsclient/tfs_compat/grpc/serving_client.py
ovmsclient/tfs_compat/grpc/tensors.py
ovmsclient/tfs_compat/http/__init__.py
ovmsclient/tfs_compat/http/requests.py
ovmsclient/tfs_compat/http/responses.py
ovmsclient/tfs_compat/http/serving_client.py
ovmsclient/tfs_compat/protos/tensorflow/core/example/example_parser_configuration_pb2.py
ovmsclient/tfs_compat/protos/tensorflow/core/example/example_pb2.py
ovmsclient/tfs_compat/protos/tensorflow/core/example/feature_pb2.py
ovmsclient/tfs_compat/protos/tensorflow/core/framework/allocation_description_pb2.py
ovmsclient/tfs_compat/protos/tensorflow/core/framework/api_def_pb2.py
ovmsclient/tfs_compat/protos/tensorflow/core/framework/attr_value_pb2.py
ovmsclient/tfs_compat/protos/tensorflow/core/framework/cost_graph_pb2.py
ovmsclient/tfs_compat/protos/tensorflow/core/framework/dataset_options_pb2.py
ovmsclient/tfs_compat/protos/tensorflow/core/framework/device_attributes_pb2.py
ovmsclient/tfs_compat/protos/tensorflow/core/framework/function_pb2.py
ovmsclient/tfs_compat/protos/tensorflow/core/framework/graph_pb2.py
ovmsclient/tfs_compat/protos/tensorflow/core/framework/graph_transfer_info_pb2.py
ovmsclient/tfs_compat/protos/tensorflow/core/framework/kernel_def_pb2.py
ovmsclient/tfs_compat/protos/tensorflow/core/framework/log_memory_pb2.py
ovmsclient/tfs_compat/protos/tensorflow/core/framework/model_pb2.py
ovmsclient/tfs_compat/protos/tensorflow/core/framework/node_def_pb2.py
ovmsclient/tfs_compat/protos/tensorflow/core/framework/op_def_pb2.py
ovmsclient-2023.1.dist-info/METADATA
ovmsclient-2023.1.dist-info/WHEEL
ovmsclient-2023.1.dist-info/top_level.txt
ovmsclient-2023.1.dist-info/RECORD
