Metadata-Version: 2.1
Name: ovmsclient
Version: 2023.1
Summary: Python client for OpenVINO Model Server
Home-page: https://github.com/openvinotoolkit/model_server/tree/releases/2023/1/client/python/ovmsclient/lib
Author: Intel Corporation
Author-email: ovms.engineering@intel.com
License: Apache License 2.0
Platform: UNKNOWN
Requires-Dist: grpcio (>=1.47.0)
Requires-Dist: numpy (>=1.16.6)
Requires-Dist: protobuf (>=3.19.4)
Requires-Dist: requests (>=2.27.1)
